{"seed_index": 4, "query_num": 19, "viewport": {"x": 9, "y": 1, "w": 15, "h": 15}, "grid": [[11, 4, 11, 11, 4, 11, 4, 11, 11, 11, 2, 11, 11, 11, 4], [4, 11, 11, 4, 4, 11, 4, 4, 4, 11, 1, 11, 4, 4, 11], [11, 11, 11, 11, 11, 11, 11, 4, 11, 1, 1, 1, 11, 11, 1], [4, 11, 1, 11, 11, 1, 11, 11, 1, 11, 1, 1, 1, 11, 11], [11, 11, 1, 1, 11, 4, 1, 11, 11, 11, 11, 1, 11, 11, 11], [10, 10, 11, 1, 11, 11, 11, 11, 11, 4, 11, 11, 11, 11, 1], [11, 10, 11, 11, 4, 11, 11, 1, 1, 1, 11, 1, 11, 4, 1], [11, 4, 10, 11, 11, 11, 1, 11, 11, 11, 11, 4, 11, 11, 1], [4, 11, 11, 10, 10, 11, 1, 11, 1, 11, 1, 11, 11, 1, 1], [11, 11, 11, 10, 10, 11, 11, 1, 11, 4, 11, 11, 11, 11, 4], [4, 11, 11, 4, 10, 11, 1, 1, 11, 11, 11, 1, 11, 11, 11], [4, 11, 2, 10, 10, 4, 4, 4, 11, 4, 1, 11, 1, 1, 1], [11, 11, 4, 11, 4, 1, 11, 4, 1, 1, 11, 1, 1, 4, 11], [11, 4, 11, 4, 4, 1, 1, 4, 11, 11, 1, 11, 11, 11, 11], [11, 11, 4, 11, 11, 4, 4, 11, 11, 11, 11, 11, 1, 4, 11]], "settlements": [{"x": 14, "y": 13, "population": 2.462, "food": 0.811, "wealth": 0.011, "defense": 1.0, "has_port": false, "alive": true, "owner_id": 38}, {"x": 15, "y": 8, "population": 2.584, "food": 0.536, "wealth": 0.018, "defense": 1.0, "has_port": false, "alive": true, "owner_id": 38}, {"x": 21, "y": 4, "population": 2.513, "food": 0.807, "wealth": 0.016, "defense": 1.0, "has_port": false, "alive": true, "owner_id": 6}, {"x": 21, "y": 13, "population": 3.217, "food": 0.68, "wealth": 0.034, "defense": 1.0, "has_port": false, "alive": true, "owner_id": 17}, {"x": 12, "y": 6, "population": 2.662, "food": 0.374, "wealth": 0.012, "defense": 1.0, "has_port": false, "alive": true, "owner_id": 5}, {"x": 23, "y": 6, "population": 2.436, "food": 0.321, "wealth": 0.025, "defense": 1.0, "has_port": false, "alive": true, "owner_id": 8}, {"x": 17, "y": 4, "population": 2.302, "food": 0.823, "wealth": 0.01, "defense": 1.0, "has_port": false, "alive": true, "owner_id": 6}, {"x": 20, "y": 11, "population": 2.247, "food": 0.828, "wealth": 0.012, "defense": 1.0, "has_port": false, "alive": true, "owner_id": 17}, {"x": 17, "y": 9, "population": 2.034, "food": 0.844, "wealth": 0.003, "defense": 1.0, "has_port": false, "alive": true, "owner_id": 38}, {"x": 21, "y": 15, "population": 1.828, "food": 0.849, "wealth": 0.01, "defense": 1.0, "has_port": false, "alive": true, "owner_id": 17}, {"x": 14, "y": 14, "population": 1.512, "food": 0.653, "wealth": 0.005, "defense": 1.0, "has_port": false, "alive": true, "owner_id": 38}, {"x": 11, "y": 12, "population": 1.244, "food": 0.905, "wealth": 0.004, "defense": 0.69, "has_port": true, "alive": true, "owner_id": 38}, {"x": 18, "y": 3, "population": 1.68, "food": 0.871, "wealth": 0.005, "defense": 1.0, "has_port": false, "alive": true, "owner_id": 6}, {"x": 19, "y": 1, "population": 1.564, "food": 0.88, "wealth": 0.0, "defense": 0.966, "has_port": true, "alive": true, "owner_id": 6}, {"x": 19, "y": 2, "population": 1.515, "food": 0.884, "wealth": 0.0, "defense": 0.913, "has_port": false, "alive": true, "owner_id": 6}, {"x": 11, "y": 4, "population": 1.502, "food": 0.885, "wealth": 0.004, "defense": 0.908, "has_port": false, "alive": true, "owner_id": 5}, {"x": 15, "y": 5, "population": 0.542, "food": 0.758, "wealth": 0.002, "defense": 0.247, "has_port": false, "alive": true, "owner_id": 38}, {"x": 19, "y": 14, "population": 1.555, "food": 0.881, "wealth": 0.014, "defense": 1.0, "has_port": false, "alive": true, "owner_id": 17}, {"x": 20, "y": 7, "population": 0.874, "food": 0.933, "wealth": 0.002, "defense": 0.458, "has_port": false, "alive": true, "owner_id": 17}, {"x": 23, "y": 7, "population": 0.539, "food": 0.959, "wealth": 0.0, "defense": 0.272, "has_port": false, "alive": true, "owner_id": 6}, {"x": 11, "y": 5, "population": 0.688, "food": 0.907, "wealth": 0.0, "defense": 0.357, "has_port": false, "alive": true, "owner_id": 0}, {"x": 23, "y": 12, "population": 0.674, "food": 0.948, "wealth": 0.002, "defense": 0.333, "has_port": false, "alive": true, "owner_id": 17}, {"x": 22, "y": 9, "population": 0.283, "food": 0.978, "wealth": 0.0, "defense": 0.138, "has_port": false, "alive": true, "owner_id": 1}, {"x": 23, "y": 3, "population": 0.332, "food": 0.975, "wealth": 0.0, "defense": 0.156, "has_port": false, "alive": true, "owner_id": 8}, {"x": 18, "y": 13, "population": 0.54, "food": 0.959, "wealth": 0.001, "defense": 0.285, "has_port": false, "alive": true, "owner_id": 17}, {"x": 12, "y": 5, "population": 0.747, "food": 0.943, "wealth": 0.001, "defense": 0.402, "has_port": false, "alive": true, "owner_id": 5}, {"x": 17, "y": 13, "population": 0.705, "food": 0.946, "wealth": 0.002, "defense": 0.35, "has_port": false, "alive": true, "owner_id": 38}, {"x": 20, "y": 3, "population": 1.035, "food": 0.921, "wealth": 0.004, "defense": 0.514, "has_port": false, "alive": true, "owner_id": 6}, {"x": 18, "y": 7, "population": 0.938, "food": 0.728, "wealth": 0.0, "defense": 0.335, "has_port": false, "alive": true, "owner_id": 17}, {"x": 19, "y": 12, "population": 0.768, "food": 0.941, "wealth": 0.003, "defense": 0.398, "has_port": false, "alive": true, "owner_id": 17}, {"x": 23, "y": 9, "population": 0.907, "food": 0.93, "wealth": 0.001, "defense": 0.48, "has_port": false, "alive": true, "owner_id": 1}, {"x": 15, "y": 14, "population": 0.429, "food": 0.967, "wealth": 0.0, "defense": 0.216, "has_port": false, "alive": true, "owner_id": 45}, {"x": 20, "y": 4, "population": 0.526, "food": 0.746, "wealth": 0.002, "defense": 0.325, "has_port": false, "alive": true, "owner_id": 6}, {"x": 21, "y": 12, "population": 0.722, "food": 0.945, "wealth": 0.002, "defense": 0.374, "has_port": false, "alive": true, "owner_id": 17}, {"x": 17, "y": 7, "population": 0.584, "food": 0.955, "wealth": 0.004, "defense": 0.284, "has_port": false, "alive": true, "owner_id": 38}, {"x": 16, "y": 11, "population": 0.561, "food": 0.957, "wealth": 0.0, "defense": 0.266, "has_port": false, "alive": true, "owner_id": 38}, {"x": 20, "y": 5, "population": 0.534, "food": 0.959, "wealth": 0.0, "defense": 0.259, "has_port": false, "alive": true, "owner_id": 6}, {"x": 15, "y": 9, "population": 0.651, "food": 0.95, "wealth": 0.003, "defense": 0.305, "has_port": false, "alive": true, "owner_id": 38}, {"x": 19, "y": 4, "population": 0.563, "food": 0.756, "wealth": 0.003, "defense": 0.292, "has_port": false, "alive": true, "owner_id": 6}, {"x": 19, "y": 3, "population": 0.563, "food": 0.659, "wealth": 0.003, "defense": 0.292, "has_port": false, "alive": true, "owner_id": 6}, {"x": 22, "y": 12, "population": 0.607, "food": 0.953, "wealth": 0.003, "defense": 0.297, "has_port": false, "alive": true, "owner_id": 17}, {"x": 16, "y": 7, "population": 0.604, "food": 0.954, "wealth": 0.001, "defense": 0.297, "has_port": false, "alive": true, "owner_id": 38}, {"x": 16, "y": 10, "population": 0.55, "food": 0.761, "wealth": 0.004, "defense": 0.262, "has_port": false, "alive": true, "owner_id": 38}, {"x": 20, "y": 13, "population": 0.553, "food": 0.722, "wealth": 0.003, "defense": 0.262, "has_port": false, "alive": true, "owner_id": 17}, {"x": 19, "y": 9, "population": 0.231, "food": 0.686, "wealth": 0.0, "defense": 0.09, "has_port": false, "alive": true, "owner_id": 38}, {"x": 23, "y": 8, "population": 0.5, "food": 0.442, "wealth": 0.002, "defense": 0.229, "has_port": false, "alive": true, "owner_id": 14}, {"x": 14, "y": 4, "population": 0.5, "food": 0.335, "wealth": 0.003, "defense": 0.2, "has_port": false, "alive": true, "owner_id": 5}, {"x": 15, "y": 11, "population": 0.5, "food": 0.193, "wealth": 0.001, "defense": 0.2, "has_port": false, "alive": true, "owner_id": 38}], "is_repeat": false}