{"seed_index": 2, "query_num": 7, "viewport": {"x": 24, "y": 19, "w": 15, "h": 15}, "grid": [[4, 1, 11, 11, 4, 11, 1, 11, 11, 1, 11, 11, 11, 11, 11], [11, 11, 11, 4, 11, 11, 11, 11, 11, 4, 11, 11, 4, 11, 11], [11, 11, 1, 11, 11, 1, 11, 11, 11, 11, 1, 11, 1, 11, 4], [1, 1, 1, 4, 11, 11, 1, 4, 1, 4, 1, 11, 4, 11, 4], [11, 11, 1, 4, 11, 1, 1, 5, 1, 1, 11, 11, 11, 11, 11], [11, 11, 11, 11, 4, 4, 5, 11, 11, 1, 11, 4, 11, 11, 11], [11, 11, 4, 11, 11, 1, 4, 11, 1, 4, 11, 1, 1, 4, 11], [1, 11, 4, 1, 5, 4, 1, 4, 11, 11, 11, 11, 4, 11, 11], [11, 5, 11, 5, 5, 11, 4, 5, 1, 11, 1, 11, 1, 11, 11], [5, 5, 1, 11, 5, 5, 5, 5, 5, 1, 11, 1, 4, 1, 11], [11, 4, 5, 11, 11, 5, 5, 11, 11, 1, 4, 11, 11, 11, 11], [11, 11, 4, 11, 4, 4, 1, 4, 4, 11, 11, 11, 1, 11, 4], [11, 1, 11, 11, 1, 11, 11, 1, 1, 1, 11, 11, 1, 11, 11], [11, 1, 11, 1, 11, 11, 11, 11, 4, 11, 11, 11, 11, 11, 4], [11, 11, 1, 1, 4, 1, 11, 4, 1, 11, 3, 1, 1, 1, 11]], "settlements": [{"x": 32, "y": 31, "population": 1.689, "food": 0.345, "wealth": 0.012, "defense": 1.0, "has_port": false, "alive": true, "owner_id": 3}, {"x": 26, "y": 23, "population": 2.434, "food": 0.401, "wealth": 0.009, "defense": 1.0, "has_port": false, "alive": true, "owner_id": 38}, {"x": 36, "y": 30, "population": 2.192, "food": 0.613, "wealth": 0.009, "defense": 1.0, "has_port": false, "alive": true, "owner_id": 24}, {"x": 30, "y": 22, "population": 2.628, "food": 0.565, "wealth": 0.004, "defense": 1.0, "has_port": false, "alive": true, "owner_id": 38}, {"x": 35, "y": 28, "population": 1.996, "food": 0.825, "wealth": 0.009, "defense": 1.0, "has_port": false, "alive": true, "owner_id": 24}, {"x": 31, "y": 31, "population": 2.025, "food": 0.755, "wealth": 0.004, "defense": 1.0, "has_port": false, "alive": true, "owner_id": 3}, {"x": 32, "y": 27, "population": 1.448, "food": 0.628, "wealth": 0.009, "defense": 0.979, "has_port": false, "alive": true, "owner_id": 38}, {"x": 24, "y": 26, "population": 1.827, "food": 0.691, "wealth": 0.004, "defense": 1.0, "has_port": false, "alive": true, "owner_id": 38}, {"x": 27, "y": 26, "population": 2.014, "food": 0.368, "wealth": 0.005, "defense": 1.0, "has_port": false, "alive": true, "owner_id": 38}, {"x": 26, "y": 33, "population": 1.794, "food": 0.319, "wealth": 0.004, "defense": 1.0, "has_port": false, "alive": true, "owner_id": 3}, {"x": 34, "y": 21, "population": 1.791, "food": 0.639, "wealth": 0.002, "defense": 1.0, "has_port": false, "alive": true, "owner_id": 38}, {"x": 35, "y": 25, "population": 2.018, "food": 0.823, "wealth": 0.003, "defense": 1.0, "has_port": false, "alive": true, "owner_id": 24}, {"x": 37, "y": 33, "population": 1.824, "food": 0.706, "wealth": 0.003, "defense": 1.0, "has_port": false, "alive": true, "owner_id": 24}, {"x": 33, "y": 23, "population": 1.617, "food": 0.704, "wealth": 0.003, "defense": 1.0, "has_port": false, "alive": true, "owner_id": 38}, {"x": 27, "y": 33, "population": 1.608, "food": 0.428, "wealth": 0.002, "defense": 1.0, "has_port": false, "alive": true, "owner_id": 3}, {"x": 32, "y": 25, "population": 1.035, "food": 0.709, "wealth": 0.001, "defense": 0.417, "has_port": false, "alive": true, "owner_id": 24}, {"x": 28, "y": 31, "population": 1.722, "food": 0.849, "wealth": 0.001, "defense": 1.0, "has_port": false, "alive": true, "owner_id": 3}, {"x": 33, "y": 19, "population": 1.595, "food": 0.86, "wealth": 0.003, "defense": 1.0, "has_port": false, "alive": true, "owner_id": 38}, {"x": 24, "y": 22, "population": 1.573, "food": 0.862, "wealth": 0.004, "defense": 0.74, "has_port": false, "alive": true, "owner_id": 38}, {"x": 30, "y": 26, "population": 1.573, "food": 0.862, "wealth": 0.002, "defense": 0.74, "has_port": false, "alive": true, "owner_id": 38}, {"x": 33, "y": 31, "population": 0.937, "food": 0.871, "wealth": 0.003, "defense": 0.356, "has_port": false, "alive": true, "owner_id": 3}, {"x": 29, "y": 21, "population": 1.201, "food": 0.895, "wealth": 0.001, "defense": 0.482, "has_port": false, "alive": true, "owner_id": 38}, {"x": 34, "y": 27, "population": 0.77, "food": 0.933, "wealth": 0.001, "defense": 0.27, "has_port": false, "alive": true, "owner_id": 24}, {"x": 26, "y": 21, "population": 1.144, "food": 0.9, "wealth": 0.001, "defense": 0.46, "has_port": false, "alive": true, "owner_id": 38}, {"x": 36, "y": 27, "population": 1.138, "food": 0.9, "wealth": 0.003, "defense": 0.459, "has_port": false, "alive": true, "owner_id": 24}, {"x": 36, "y": 33, "population": 0.868, "food": 0.924, "wealth": 0.002, "defense": 0.327, "has_port": false, "alive": true, "owner_id": 24}, {"x": 36, "y": 21, "population": 1.144, "food": 0.9, "wealth": 0.001, "defense": 0.46, "has_port": false, "alive": true, "owner_id": 38}, {"x": 25, "y": 19, "population": 1.144, "food": 0.9, "wealth": 0.001, "defense": 0.46, "has_port": false, "alive": true, "owner_id": 38}, {"x": 33, "y": 24, "population": 0.705, "food": 0.938, "wealth": 0.001, "defense": 0.259, "has_port": false, "alive": true, "owner_id": 38}, {"x": 26, "y": 28, "population": 0.644, "food": 0.744, "wealth": 0.001, "defense": 0.209, "has_port": false, "alive": true, "owner_id": 38}, {"x": 35, "y": 33, "population": 0.481, "food": 0.958, "wealth": 0.001, "defense": 0.179, "has_port": false, "alive": true, "owner_id": 24}, {"x": 25, "y": 22, "population": 0.787, "food": 0.827, "wealth": 0.0, "defense": 0.275, "has_port": false, "alive": true, "owner_id": 38}, {"x": 26, "y": 22, "population": 0.502, "food": 0.419, "wealth": 0.0, "defense": 0.234, "has_port": false, "alive": true, "owner_id": 38}, {"x": 25, "y": 31, "population": 0.55, "food": 0.952, "wealth": 0.001, "defense": 0.192, "has_port": false, "alive": true, "owner_id": 3}, {"x": 27, "y": 32, "population": 0.815, "food": 0.929, "wealth": 0.0, "defense": 0.305, "has_port": false, "alive": true, "owner_id": 3}, {"x": 29, "y": 33, "population": 0.82, "food": 0.928, "wealth": 0.001, "defense": 0.306, "has_port": false, "alive": true, "owner_id": 3}, {"x": 30, "y": 23, "population": 0.715, "food": 0.383, "wealth": 0.002, "defense": 0.265, "has_port": false, "alive": true, "owner_id": 38}, {"x": 37, "y": 28, "population": 0.713, "food": 0.938, "wealth": 0.002, "defense": 0.265, "has_port": false, "alive": true, "owner_id": 24}, {"x": 33, "y": 29, "population": 0.334, "food": 0.672, "wealth": 0.001, "defense": 0.103, "has_port": false, "alive": true, "owner_id": 38}, {"x": 32, "y": 22, "population": 0.715, "food": 0.937, "wealth": 0.001, "defense": 0.265, "has_port": false, "alive": true, "owner_id": 38}, {"x": 29, "y": 23, "population": 0.715, "food": 0.926, "wealth": 0.001, "defense": 0.265, "has_port": false, "alive": true, "owner_id": 38}, {"x": 25, "y": 32, "population": 0.72, "food": 0.725, "wealth": 0.0, "defense": 0.266, "has_port": false, "alive": true, "owner_id": 3}, {"x": 30, "y": 19, "population": 0.715, "food": 0.937, "wealth": 0.001, "defense": 0.265, "has_port": false, "alive": true, "owner_id": 38}, {"x": 32, "y": 33, "population": 0.607, "food": 0.626, "wealth": 0.002, "defense": 0.23, "has_port": false, "alive": true, "owner_id": 3}, {"x": 29, "y": 25, "population": 0.411, "food": 0.64, "wealth": 0.0, "defense": 0.139, "has_port": false, "alive": true, "owner_id": 38}, {"x": 32, "y": 23, "population": 0.4, "food": 0.178, "wealth": 0.0, "defense": 0.17, "has_port": false, "alive": true, "owner_id": 38}, {"x": 36, "y": 31, "population": 0.483, "food": 0.401, "wealth": 0.0, "defense": 0.174, "has_port": false, "alive": true, "owner_id": 3}, {"x": 36, "y": 25, "population": 0.386, "food": 0.422, "wealth": 0.0, "defense": 0.122, "has_port": false, "alive": true, "owner_id": 24}, {"x": 30, "y": 30, "population": 0.425, "food": 0.301, "wealth": 0.003, "defense": 0.16, "has_port": false, "alive": true, "owner_id": 3}, {"x": 33, "y": 28, "population": 0.4, "food": 0.126, "wealth": 0.001, "defense": 0.15, "has_port": false, "alive": true, "owner_id": 38}, {"x": 34, "y": 22, "population": 0.4, "food": 0.18, "wealth": 0.0, "defense": 0.15, "has_port": false, "alive": true, "owner_id": 38}], "is_repeat": false}